double_o-0.1.3.dist-info/licenses/LICENSE
oo/__init__.py
oo/client.py
oo/exceptions.py
oo/py.typed
double_o-0.1.3.dist-info/METADATA
double_o-0.1.3.dist-info/WHEEL
double_o-0.1.3.dist-info/top_level.txt
double_o-0.1.3.dist-info/RECORD
